{
    "id": 129,
    "topic": "Cadillac Cyclone as a futuristic concept car and automotive design marvel",
    "description": "The 1959 Cadillac Cyclone is a groundbreaking concept car known for its futuristic design features and unique aesthetics. It embodies innovation and imagination in automotive design, pushing the boundaries of what a car can be.",
    "depth": 0,
    "children": [
        {
            "id": 130,
            "topic": "Innovative design elements of the 1959 Cadillac Cyclone",
            "description": "The Cadillac Cyclone showcases cutting-edge design elements such as radar-powered crash sensors, sliding bubble canopies, and moon-cutting rear tailfins. These features contribute to its futuristic and unique appearance, setting it apart from traditional car designs of its time.",
            "depth": 1,
            "children": [
                {
                    "id": 131,
                    "topic": "Radar-powered crash sensors",
                    "description": "The inclusion of radar-powered crash sensors in the 1959 Cadillac Cyclone demonstrates advanced safety technology for that era. This innovative feature enhances the car's futuristic appeal and highlights its forward-thinking design.",
                    "depth": 2,
                    "children": []
                },
                {
                    "id": 132,
                    "topic": "Sliding bubble canopies",
                    "description": "The sliding bubble canopies on the Cadillac Cyclone resemble those found on fighter jets, adding a touch of aerospace influence to the car's design. This unique feature not only enhances the vehicle's visual appeal but also showcases its futuristic and unconventional nature.",
                    "depth": 2,
                    "children": []
                },
                {
                    "id": 133,
                    "topic": "Moon-cutting rear tailfins",
                    "description": "The rear tailfins of the 1959 Cadillac Cyclone are not only aesthetically striking but also evoke a sense of speed and power. Their sharp, angular design gives the impression that they could cut through the moon, emphasizing the car's futuristic and otherworldly aesthetic.",
                    "depth": 2,
                    "children": []
                }
            ]
        },
        {
            "id": 134,
            "topic": "Exclusivity and rarity of the 1959 Cadillac Cyclone",
            "description": "The Cadillac Cyclone is a one-off concept car that was never mass-produced, residing exclusively in the GM Heritage Collection. Its limited availability and unique status as a crown jewel in a vault contribute to its mystique and allure as a rare automotive gem.",
            "depth": 1,
            "children": [
                {
                    "id": 135,
                    "topic": "24k gold-plated wheels",
                    "description": "The 1959 Cadillac Cyclone features 24k gold-plated wheels, adding a luxurious and extravagant touch to its design. This exclusive feature enhances the car's status as a unique and valuable collector's item, further emphasizing its rarity and desirability.",
                    "depth": 2,
                    "children": []
                },
                {
                    "id": 136,
                    "topic": "GM Heritage Collection",
                    "description": "The Cadillac Cyclone is housed in the GM Heritage Collection, where it is preserved as a significant piece of automotive history. Its presence in this exclusive collection underscores its importance as a rare and iconic concept car that represents a bygone era of innovation and design.",
                    "depth": 2,
                    "children": []
                },
                {
                    "id": 137,
                    "topic": "Crown jewel in a vault",
                    "description": "The 1959 Cadillac Cyclone is likened to a crown jewel in a vault due to its exclusive status and limited availability. This metaphor highlights the car's significance and value as a rare and precious artifact, further enhancing its mystique and desirability.",
                    "depth": 2,
                    "children": []
                }
            ]
        },
        {
            "id": 138,
            "topic": "Aesthetic appeal and cultural significance of the 1959 Cadillac Cyclone",
            "description": "The 1959 Cadillac Cyclone's striking appearance, reminiscent of a James Bond dream car dipped in pink gold, holds both aesthetic appeal and cultural significance. Its unique design elements and luxurious features contribute to its iconic status as a symbol of automotive innovation and style.",
            "depth": 1,
            "children": [
                {
                    "id": 139,
                    "topic": "James Bond dream car aesthetic",
                    "description": "The Cadillac Cyclone's design, resembling a James Bond dream car dipped in pink gold, evokes a sense of sophistication and luxury. This aesthetic appeal contributes to the car's iconic status and cultural significance, aligning it with the glamorous world of espionage and adventure.",
                    "depth": 2,
                    "children": []
                },
                {
                    "id": 140,
                    "topic": "Luxurious pink gold exterior",
                    "description": "The pink gold exterior of the 1959 Cadillac Cyclone adds a touch of luxury and opulence to its design, further enhancing its aesthetic appeal. This unique color choice sets the car apart and contributes to its cultural significance as a symbol of extravagance and style.",
                    "depth": 2,
                    "children": []
                },
                {
                    "id": 141,
                    "topic": "Iconic status in automotive history",
                    "description": "The Cadillac Cyclone's unique design features and luxurious aesthetics have cemented its iconic status in automotive history. As a symbol of innovation and style, it holds cultural significance as a timeless representation of automotive excellence and creativity.",
                    "depth": 2,
                    "children": []
                }
            ]
        }
    ]
}